logreduce/__init__.py
logreduce/cmd.py
logreduce/data.py
logreduce/download.py
logreduce/html_output.py
logreduce/models.py
logreduce/process.py
logreduce/tokenizer.py
logreduce/utils.py
logreduce/worker.py
logreduce/tests/__init__.py
logreduce/tests/test_download.py
logreduce/tests/test_html_output.py
logreduce/tests/test_process.py
logreduce/tests/test_python_api.py
logreduce/tests/test_units.py
logreduce/tests/utils.py
logreduce-0.6.1.dist-info/AUTHORS
logreduce-0.6.1.dist-info/LICENSE
logreduce-0.6.1.dist-info/METADATA
logreduce-0.6.1.dist-info/WHEEL
logreduce-0.6.1.dist-info/entry_points.txt
logreduce-0.6.1.dist-info/pbr.json
logreduce-0.6.1.dist-info/top_level.txt
logreduce-0.6.1.dist-info/RECORD
