Metadata-Version: 2.1
Name: logreduce
Version: 0.6.1
Summary: Extract anomalies from log files
Home-page: https://logreduce.softwarefactory-project.io/
Author: Tristan Cacqueray
Author-email: tdecacqu@redhat.com
License: UNKNOWN
Keywords: machine learning, ci, anomaly detection
Platform: UNKNOWN
Classifier: Intended Audience :: Developers
Classifier: Intended Audience :: System Administrators
Classifier: License :: OSI Approved :: Apache Software License
Classifier: Programming Language :: Python
Classifier: Programming Language :: Python :: 3.5
Classifier: Topic :: Scientific/Engineering
Requires-Dist: aiohttp
Requires-Dist: requests
Requires-Dist: numpy
Requires-Dist: scipy
Requires-Dist: scikit-learn
Requires-Dist: PyYAML
Requires-Dist: typing-extensions ; (python_version < '3.8')
